Workbook

Sheet Cover
B2: PhysicianLabs — 18-Month Financial Model
B3: Expense-focused cash-needs model · Concierge Hybrid revenue motion · Prepared 2026-06-30
B5: KEY RESULTS (18 months: Jul 2026 – Dec 2027)
B6: Total revenue (18-mo target ≥ $1,000,000) | C6: ='Cash Flow'!B18 -> 1125577.3
B7: Total cost of sales | C7: ='Cash Flow'!B19 -> 288452.03
B8: Total operating expenses (incl. founder draw + setup) | C8: ='Cash Flow'!B20 -> 149233.77
B9: Net cash generated over 18 months | C9: ='Cash Flow'!B21 -> 687891.54
B10: PEAK CUMULATIVE CASH NEED (financing required) | C10: ='Cash Flow'!B22 -> 17511.665
B11: Month of deepest cash position | C11: ='Cash Flow'!B23 -> 3
B12: Cash-flow breakeven (first net-positive month) | C12: ='Cash Flow'!B24 -> 4
B13: Ending cash position (Month 18) | C13: ='Cash Flow'!B25 -> 687891.54
B14: Total paying program customers acquired | C14: =Revenue!S6 -> 46
B15: Blended gross margin | C15: =('Cash Flow'!B18-'Cash Flow'!B19)/'Cash Flow'!B18 -> 0.74372971
B17: HOW THIS MODEL WORKS
B18: • Driver-based: change any blue input on the Assumptions tab and the whole model updates.
B19: • Revenue tab builds the 18-month forecast from the locked Concierge Hybrid motion:
B20: $1,000 money-back PoC → Transition Program ($8K founding / $22K standard) → $599–$799/mo.
B21: • Cost of Sales = expenses that scale with revenue (payment fees, delivery contractors,
B22: per-customer hosting). Delivery contractor cost is the "ahead-of-revenue" capacity lever.
B23: • OpEx = recurring overhead in standard categories, grown monthly, plus the founder living
B24: draw and one-time Founder Institute + incorporation setup costs.
B25: • Cash Flow tab nets it all and surfaces the peak cumulative cash need — the money you must
B26: have on hand (founder-funded or raised) to bridge to self-funding revenue.
B28: COLOR LEGEND
B29: Blue = input you can change | C29: Black = formula
B30: Green = link from another tab | C30: Yellow = headline cash number
B32: SOURCES & GROUNDING
B33: Revenue model: memory "project-one-revenue-model-jun2026" (Concierge Hybrid, locked 2026-06-20).
B34: Pricing ladder & $1M/18-mo reconciliation: docs/business-development/business-plan.md → Pricing Architecture.
B35: Price points & cohort: docs/customer-development/revenue-interview-pricing-guide-2026-06-20.md.
B36: Timing / sales cycle: docs/business-development/buyer-journey-2026-06-20.md (short cycle, revenue in 14–30 days).
B37: Founder Institute entrance fee ~$799–$999 + 2.5% equity warrant (non-cash): fi.co/core, fi.co/faq (June 2026).
B38: Expenses-to-date inferred from tools in use (AI/dev subscription, domain physicianlab.com, FI program) —
B39: no formal expense ledger exists in the repo; setup costs grounded to FI + standard US incorporation.
B41: NOTE: This is a planning model, not accounting or investment advice. The peak cash need assumes the documented fast PoC→program conversion; if the first program slips a month or two, or the founder draw rises, the cash need deepens — flex the Assumptions tab to stress it.

Sheet Assumptions
A1: Assumptions — all blue cells are inputs you can change
A2: Driver | B2: Value | C2: Note
A4: REVENUE DRIVERS
A5: PoC price (one-time, money-back) | B5: 1000 | C5: Validated entry offer; refunded if <$20K recoverable found
A6: Transition Program — Founding (first 10) | B6: 8000 | C6: Founding-cohort price, first 10 customers
A7: Transition Program — Standard | B7: 22000 | C7: Standard list price; ~40–46 customers ≈ $1M / 18 mo
A8: Subscription — Founding ($/mo) | B8: 599 | C8: Founder rate, locked for life
A9: Subscription — Standard ($/mo) | B9: 799 | C9: Standard recurring tier
A10: Founding-cohort cap (customers) | B10: 10 | C10: First 10 get the $8K founding price; rest pay standard
A11: PoC → Program conversion rate | B11: 0.65 | C11: Share of PoC buyers who buy the program
A12: PoC refund / decline rate | B12: 0.1 | C12: Money-back PoCs that get refunded
A13: Monthly subscription churn | B13: 0.02 | C13: Plan target <2%/mo
A15: COST OF SALES DRIVERS (scale with revenue)
A16: Payment processing — % of revenue | B16: 0.029 | C16: Stripe ~2.9%
A17: Payment processing — $/transaction | B17: 0.3 | C17: Stripe ~$0.30 per charge
A18: Delivery contractor cost / Founding program | B18: 2500 | C18: Fractional credentialing/billing help
A19: Delivery contractor cost / Standard program | B19: 6000 | C19: Done-for-you delivery labor (ahead-of-revenue lever)
A20: PoC audit direct cost / PoC | B20: 75 | C20: Data pulls / tooling per 90-min audit
A21: Hosting & support / active subscriber / mo | B21: 35 | C21: Keeps SaaS-tier gross margin >90%
A23: OPERATING EXPENSE DRIVERS (recurring overhead)
A24: Founder living draw ($/mo) | B24: 6000 | C24: Your personal living expenses — biggest cash lever
A25: Software & subscriptions — base $/mo | B25: 350 | C25: AI/dev (Claude), Workspace, CRM, accounting, hosting
A26: Software & subscriptions — monthly growth | B26: 0.03 | C26: Compounding tool spend as usage grows
A27: Sales & marketing — base $/mo | B27: 300 | C27: Content, community, case studies, light ads, travel
A28: Sales & marketing — monthly growth | B28: 0.05 | C28: Scales ahead of revenue to build pipeline
A29: Accounting & bookkeeping ($/mo) | B29: 250 | C29: Bookkeeping + tax prep amortized
A30: Insurance — E&O / professional liability ($/mo) | B30: 150 | C30: Needed: advisory / done-for-you financial work
A31: Insurance start month (#) | B31: 3 | C31: Starts once first program client signs
A32: Office / admin / misc ($/mo) | B32: 150 | C32: Bank fees, phone, contingency
A33: Contract admin / VA ($/mo) | B33: 1200 | C33: Part-time ops support as volume grows
A34: Contract admin / VA start month (#) | B34: 9 | C34: Added when delivery load exceeds founder capacity
A36: ONE-TIME BUSINESS SETUP (Founder Institute + incorporation)
A37: Founder Institute entrance fee | B37: 899 | C37: ~$799 early / $999 late (fi.co); refundable pre-Rev&BizModels session
A38: Incorporation (Stripe Atlas / C-corp filing) | B38: 500 | C38: Delaware C-corp via Stripe Atlas (~$500)
A39: Registered agent (annual) | B39: 100 | C39: Required for the entity
A40: Legal templates (MSA, money-back terms, advisor agts) | B40: 1500 | C40: Contracts to charge PoC + program safely
A41: Legal templates spend month (#) | B41: 2 | C41: Before first program closes
A43: Note: Founder Institute also takes a 2.5% equity warrant (non-cash) — excluded from this cash model.

Sheet Revenue
A1: Revenue Forecast — Concierge Hybrid (PoC → Program → Subscription)
A2: Month | B2: 1 | C2: 2 | D2: 3 | E2: 4 | F2: 5 | G2: 6 | H2: 7 | I2: 8 | J2: 9 | K2: 10 | L2: 11 | M2: 12 | N2: 13 | O2: 14 | P2: 15 | Q2: 16 | R2: 17 | S2: 18
A3: Period | B3: Jul-26 | C3: Aug-26 | D3: Sep-26 | E3: Oct-26 | F3: Nov-26 | G3: Dec-26 | H3: Jan-27 | I3: Feb-27 | J3: Mar-27 | K3: Apr-27 | L3: May-27 | M3: Jun-27 | N3: Jul-27 | O3: Aug-27 | P3: Sep-27 | Q3: Oct-27 | R3: Nov-27 | S3: Dec-27
A5: CUSTOMERS
A6: New program customers / month | B6: 0 | C6: 0 | D6: 1 | E6: 1 | F6: 2 | G6: 2 | H6: 3 | I6: 3 | J6: 3 | K6: 3 | L6: 3 | M6: 3 | N6: 3 | O6: 3 | P6: 4 | Q6: 4 | R6: 4 | S6: 4
A7: Cumulative customers | B7: =B6 -> 0 | C7: =B7+C6 -> 0 | D7: =C7+D6 -> 1 | E7: =D7+E6 -> 2 | F7: =E7+F6 -> 4 | G7: =F7+G6 -> 6 | H7: =G7+H6 -> 9 | I7: =H7+I6 -> 12 | J7: =I7+J6 -> 15 | ... S7: =R7+S6 -> 46
A8: of which — Founding (≤ cap) | B8: =MIN(Assumptions!$B$10,B7) -> 0 | C8: =MIN(Assumptions!$B$10,C7)-MIN(Assumptions!$B$10,B7) -> 0 | D8: =MIN(Assumptions!$B$10,D7)-MIN(Assumptions!$B$10,C7) -> 1 | E8: =MIN(Assumptions!$B$10,E7)-MIN(Assumptions!$B$10,D7) -> 1 | F8: =MIN(Assumptions!$B$10,F7)-MIN(Assumptions!$B$10,E7) -> 2 | G8: =MIN(Assumptions!$B$10,G7)-MIN(Assumptions!$B$10,F7) -> 2 | H8: =MIN(Assumptions!$B$10,H7)-MIN(Assumptions!$B$10,G7) -> 3 | I8: =MIN(Assumptions!$B$10,I7)-MIN(Assumptions!$B$10,H7) -> 1 | J8: =MIN(Assumptions!$B$10,J7)-MIN(Assumptions!$B$10,I7) -> 0 | ... S8: =MIN(Assumptions!$B$10,S7)-MIN(Assumptions!$B$10,R7) -> 0
A9: of which — Standard | B9: =B6-B8 -> 0 | C9: =C6-C8 -> 0 | D9: =D6-D8 -> 0 | E9: =E6-E8 -> 0 | F9: =F6-F8 -> 0 | G9: =G6-G8 -> 0 | H9: =H6-H8 -> 0 | I9: =I6-I8 -> 2 | ... S9: =S6-S8 -> 4
A10: PROOF-OF-CONCEPT (entry offer)
A11: New PoCs sold | B11: =ROUND(B6/Assumptions!$B$11,0) -> 0 | C11: =ROUND(C6/Assumptions!$B$11,0) -> 0 | D11: =ROUND(D6/Assumptions!$B$11,0) -> 2 | E11: =ROUND(E6/Assumptions!$B$11,0) -> 2 | F11: =ROUND(F6/Assumptions!$B$11,0) -> 3 | G11: =ROUND(G6/Assumptions!$B$11,0) -> 3 | H11: =ROUND(H6/Assumptions!$B$11,0) -> 5 | I11: =ROUND(I6/Assumptions!$B$11,0) -> 5 | ... S11: =ROUND(S6/Assumptions!$B$11,0) -> 6
A12: PoC gross revenue | B12: =B11*Assumptions!$B$5 -> 0 | C12: =C11*Assumptions!$B$5 -> 0 | D12: =D11*Assumptions!$B$5 -> 2000 | E12: =E11*Assumptions!$B$5 -> 2000 | F12: =F11*Assumptions!$B$5 -> 3000 | G12: =G11*Assumptions!$B$5 -> 3000 | H12: =H11*Assumptions!$B$5 -> 5000 | I12: =I11*Assumptions!$B$5 -> 5000 | ... S12: =S11*Assumptions!$B$5 -> 6000
A13: PoC refunds | B13: =-B12*Assumptions!$B$12 -> 0 | C13: =-C12*Assumptions!$B$12 -> 0 | D13: =-D12*Assumptions!$B$12 -> -200 | E13: =-E12*Assumptions!$B$12 -> -200 | F13: =-F12*Assumptions!$B$12 -> -300 | G13: =-G12*Assumptions!$B$12 -> -300 | H13: =-H12*Assumptions!$B$12 -> -500 | I13: =-I12*Assumptions!$B$12 -> -500 | ... S13: =-S12*Assumptions!$B$12 -> -600
A14: PoC net revenue | B14: =B12+B13 -> 0 | C14: =C12+C13 -> 0 | D14: =D12+D13 -> 1800 | E14: =E12+E13 -> 1800 | F14: =F12+F13 -> 2700 | G14: =G12+G13 -> 2700 | H14: =H12+H13 -> 4500 | I14: =I12+I13 -> 4500 | ... S14: =S12+S13 -> 5400
A15: TRANSITION PROGRAM (one-time, done-for-you)
A16: Program revenue — Founding | B16: =B8*Assumptions!$B$6 -> 0 | C16: =C8*Assumptions!$B$6 -> 0 | D16: =D8*Assumptions!$B$6 -> 8000 | E16: =E8*Assumptions!$B$6 -> 8000 | F16: =F8*Assumptions!$B$6 -> 16000 | G16: =G8*Assumptions!$B$6 -> 16000 | H16: =H8*Assumptions!$B$6 -> 24000 | I16: =I8*Assumptions!$B$6 -> 8000 | ... S16: =S8*Assumptions!$B$6 -> 0
A17: Program revenue — Standard | B17: =B9*Assumptions!$B$7 -> 0 | C17: =C9*Assumptions!$B$7 -> 0 | D17: =D9*Assumptions!$B$7 -> 0 | E17: =E9*Assumptions!$B$7 -> 0 | F17: =F9*Assumptions!$B$7 -> 0 | G17: =G9*Assumptions!$B$7 -> 0 | H17: =H9*Assumptions!$B$7 -> 0 | I17: =I9*Assumptions!$B$7 -> 44000 | ... S17: =S9*Assumptions!$B$7 -> 88000
A18: Total program revenue | B18: =B16+B17 -> 0 | C18: =C16+C17 -> 0 | D18: =D16+D17 -> 8000 | E18: =E16+E17 -> 8000 | F18: =F16+F17 -> 16000 | G18: =G16+G17 -> 16000 | H18: =H16+H17 -> 24000 | I18: =I16+I17 -> 52000 | ... S18: =S16+S17 -> 88000
A19: SUBSCRIPTION (recurring, starts month after signup)
A20: New founding subs (lag 1 mo) | B20: =0 -> 0 | C20: =B8 -> 0 | D20: =C8 -> 0 | E20: =D8 -> 1 | F20: =E8 -> 1 | G20: =F8 -> 2 | H20: =G8 -> 2 | I20: =H8 -> 3 | J20: =I8 -> 1 | ... S20: =R8 -> 0
A21: Active founding subscribers | B21: =B20 -> 0 | C21: =B21*(1-Assumptions!$B$13)+C20 -> 0 | D21: =C21*(1-Assumptions!$B$13)+D20 -> 0 | E21: =D21*(1-Assumptions!$B$13)+E20 -> 1 | F21: =E21*(1-Assumptions!$B$13)+F20 -> 1.98 | G21: =F21*(1-Assumptions!$B$13)+G20 -> 3.9404 | H21: =G21*(1-Assumptions!$B$13)+H20 -> 5.861592 | I21: =H21*(1-Assumptions!$B$13)+I20 -> 8.7443602 | J21: =I21*(1-Assumptions!$B$13)+J20 -> 9.569473 | ... S21: =R21*(1-Assumptions!$B$13)+S20 -> 7.9785267
A22: New standard subs (lag 1 mo) | B22: =0 -> 0 | C22: =B9 -> 0 | D22: =C9 -> 0 | E22: =D9 -> 0 | F22: =E9 -> 0 | G22: =F9 -> 0 | H22: =G9 -> 0 | I22: =H9 -> 0 | J22: =I9 -> 2 | ... S22: =R9 -> 4
A23: Active standard subscribers | B23: =B22 -> 0 | C23: =B23*(1-Assumptions!$B$13)+C22 -> 0 | D23: =C23*(1-Assumptions!$B$13)+D22 -> 0 | E23: =D23*(1-Assumptions!$B$13)+E22 -> 0 | F23: =E23*(1-Assumptions!$B$13)+F22 -> 0 | G23: =F23*(1-Assumptions!$B$13)+G22 -> 0 | H23: =G23*(1-Assumptions!$B$13)+H22 -> 0 | I23: =H23*(1-Assumptions!$B$13)+I22 -> 0 | J23: =I23*(1-Assumptions!$B$13)+J22 -> 2 | ... S23: =R23*(1-Assumptions!$B$13)+S22 -> 29.545731
A24: Subscription MRR | B24: =B21*Assumptions!$B$8+B23*Assumptions!$B$9 -> 0 | C24: =C21*Assumptions!$B$8+C23*Assumptions!$B$9 -> 0 | D24: =D21*Assumptions!$B$8+D23*Assumptions!$B$9 -> 0 | E24: =E21*Assumptions!$B$8+E23*Assumptions!$B$9 -> 599 | F24: =F21*Assumptions!$B$8+F23*Assumptions!$B$9 -> 1186.02 | G24: =G21*Assumptions!$B$8+G23*Assumptions!$B$9 -> 2360.2996 | H24: =H21*Assumptions!$B$8+H23*Assumptions!$B$9 -> 3511.0936 | I24: =I21*Assumptions!$B$8+I23*Assumptions!$B$9 -> 5237.8717 | ... S24: =S21*Assumptions!$B$8+S23*Assumptions!$B$9 -> 28386.177
A25: TOTAL REVENUE
A26: Total revenue | B26: =B14+B18+B24 -> 0 | C26: =C14+C18+C24 -> 0 | D26: =D14+D18+D24 -> 9800 | E26: =E14+E18+E24 -> 10399 | F26: =F14+F18+F24 -> 19886.02 | G26: =G14+G18+G24 -> 21060.3 | H26: =H14+H18+H24 -> 32011.094 | I26: =I14+I18+I24 -> 61737.872 | ... S26: =S14+S18+S24 -> 121786.18
A27: Cumulative revenue | B27: =B26 -> 0 | C27: =B27+C26 -> 0 | D27: =C27+D26 -> 9800 | E27: =D27+E26 -> 20199 | F27: =E27+F26 -> 40085.02 | G27: =F27+G26 -> 61145.32 | H27: =G27+H26 -> 93156.413 | I27: =H27+I26 -> 154894.28 | J27: =I27+J26 -> 232724.4 | ... S27: =R27+S26 -> 1125577.3
A29: $1M check: total 18-mo revenue = $1,125,577 (target ≥ $1,000,000)

Sheet Cost of Sales
A1: Cost of Sales (COGS) — expenses that scale with / ahead of revenue
A2: Month | B2: 1 | C2: 2 | D2: 3 | E2: 4 | F2: 5 | G2: 6 | H2: 7 | I2: 8 | J2: 9 | K2: 10 | L2: 11 | M2: 12 | N2: 13 | O2: 14 | P2: 15 | Q2: 16 | R2: 17 | S2: 18
A3: Period | B3: Jul-26 | C3: Aug-26 | D3: Sep-26 | E3: Oct-26 | F3: Nov-26 | G3: Dec-26 | H3: Jan-27 | I3: Feb-27 | J3: Mar-27 | K3: Apr-27 | L3: May-27 | M3: Jun-27 | N3: Jul-27 | O3: Aug-27 | P3: Sep-27 | Q3: Oct-27 | R3: Nov-27 | S3: Dec-27
A5: COST OF SALES
A6: Payment processing (Stripe) | B6: =Revenue!B26*Assumptions!$B$16+(Revenue!B11+Revenue!B6+Revenue!B21+Revenue!B23)*Assumptions!$B$17 -> 0 | C6: =Revenue!C26*Assumptions!$B$16+(Revenue!C11+Revenue!C6+Revenue!C21+Revenue!C23)*Assumptions!$B$17 -> 0 | D6: =Revenue!D26*Assumptions!$B$16+(Revenue!D11+Revenue!D6+Revenue!D21+Revenue!D23)*Assumptions!$B$17 -> 285.1 | E6: =Revenue!E26*Assumptions!$B$16+(Revenue!E11+Revenue!E6+Revenue!E21+Revenue!E23)*Assumptions!$B$17 -> 302.771 | F6: =Revenue!F26*Assumptions!$B$16+(Revenue!F11+Revenue!F6+Revenue!F21+Revenue!F23)*Assumptions!$B$17 -> 578.78858 | G6: =Revenue!G26*Assumptions!$B$16+(Revenue!G11+Revenue!G6+Revenue!G21+Revenue!G23)*Assumptions!$B$17 -> 613.43081 | H6: =Revenue!H26*Assumptions!$B$16+(Revenue!H11+Revenue!H6+Revenue!H21+Revenue!H23)*Assumptions!$B$17 -> 932.48019 | I6: =Revenue!I26*Assumptions!$B$16+(Revenue!I11+Revenue!I6+Revenue!I21+Revenue!I23)*Assumptions!$B$17 -> 1795.4216 | ... S6: =Revenue!S26*Assumptions!$B$16+(Revenue!S11+Revenue!S6+Revenue!S21+Revenue!S23)*Assumptions!$B$17 -> 3546.0564
A7: Delivery contractors (done-for-you) | B7: =Revenue!B8*Assumptions!$B$18+Revenue!B9*Assumptions!$B$19 -> 0 | C7: =Revenue!C8*Assumptions!$B$18+Revenue!C9*Assumptions!$B$19 -> 0 | D7: =Revenue!D8*Assumptions!$B$18+Revenue!D9*Assumptions!$B$19 -> 2500 | E7: =Revenue!E8*Assumptions!$B$18+Revenue!E9*Assumptions!$B$19 -> 2500 | F7: =Revenue!F8*Assumptions!$B$18+Revenue!F9*Assumptions!$B$19 -> 5000 | G7: =Revenue!G8*Assumptions!$B$18+Revenue!G9*Assumptions!$B$19 -> 5000 | H7: =Revenue!H8*Assumptions!$B$18+Revenue!H9*Assumptions!$B$19 -> 7500 | I7: =Revenue!I8*Assumptions!$B$18+Revenue!I9*Assumptions!$B$19 -> 14500 | ... S7: =Revenue!S8*Assumptions!$B$18+Revenue!S9*Assumptions!$B$19 -> 24000
A8: PoC audit direct cost | B8: =Revenue!B11*Assumptions!$B$20 -> 0 | C8: =Revenue!C11*Assumptions!$B$20 -> 0 | D8: =Revenue!D11*Assumptions!$B$20 -> 150 | E8: =Revenue!E11*Assumptions!$B$20 -> 150 | F8: =Revenue!F11*Assumptions!$B$20 -> 225 | G8: =Revenue!G11*Assumptions!$B$20 -> 225 | H8: =Revenue!H11*Assumptions!$B$20 -> 375 | I8: =Revenue!I11*Assumptions!$B$20 -> 375 | ... S8: =Revenue!S11*Assumptions!$B$20 -> 450
A9: Hosting & support (per subscriber) | B9: =(Revenue!B21+Revenue!B23)*Assumptions!$B$21 -> 0 | C9: =(Revenue!C21+Revenue!C23)*Assumptions!$B$21 -> 0 | D9: =(Revenue!D21+Revenue!D23)*Assumptions!$B$21 -> 0 | E9: =(Revenue!E21+Revenue!E23)*Assumptions!$B$21 -> 35 | F9: =(Revenue!F21+Revenue!F23)*Assumptions!$B$21 -> 69.3 | G9: =(Revenue!G21+Revenue!G23)*Assumptions!$B$21 -> 137.914 | H9: =(Revenue!H21+Revenue!H23)*Assumptions!$B$21 -> 205.15572 | I9: =(Revenue!I21+Revenue!I23)*Assumptions!$B$21 -> 306.05261 | ... S9: =(Revenue!S21+Revenue!S23)*Assumptions!$B$21 -> 1313.349
A10: Total cost of sales | B10: =SUM(B6:B9) -> 0 | C10: =SUM(C6:C9) -> 0 | D10: =SUM(D6:D9) -> 2935.1 | E10: =SUM(E6:E9) -> 2987.771 | F10: =SUM(F6:F9) -> 5873.0886 | G10: =SUM(G6:G9) -> 5976.3448 | H10: =SUM(H6:H9) -> 9012.6359 | I10: =SUM(I6:I9) -> 16976.474 | ... S10: =SUM(S6:S9) -> 29309.405
A11: GROSS PROFIT
A12: Revenue | B12: =Revenue!B26 -> 0 | C12: =Revenue!C26 -> 0 | D12: =Revenue!D26 -> 9800 | E12: =Revenue!E26 -> 10399 | F12: =Revenue!F26 -> 19886.02 | G12: =Revenue!G26 -> 21060.3 | H12: =Revenue!H26 -> 32011.094 | I12: =Revenue!I26 -> 61737.872 | ... S12: =Revenue!S26 -> 121786.18
A13: Gross profit | B13: =B12-B10 -> 0 | C13: =C12-C10 -> 0 | D13: =D12-D10 -> 6864.9 | E13: =E12-E10 -> 7411.229 | F13: =F12-F10 -> 14012.931 | G13: =G12-G10 -> 15083.955 | H13: =H12-H10 -> 22998.458 | I13: =I12-I10 -> 44761.398 | ... S13: =S12-S10 -> 92476.771
A14: Gross margin % | B14: =IF(B12=0,0,B13/B12) -> 0 | C14: =IF(C12=0,0,C13/C12) -> 0 | D14: =IF(D12=0,0,D13/D12) -> 0.7005 | E14: =IF(E12=0,0,E13/E12) -> 0.7126867 | F14: =IF(F12=0,0,F13/F12) -> 0.70466244 | G14: =IF(G12=0,0,G13/G12) -> 0.71622698 | H14: =IF(H12=0,0,H13/H12) -> 0.71845273 | I14: =IF(I12=0,0,I13/I12) -> 0.72502333 | ... S14: =IF(S12=0,0,S13/S12) -> 0.75933717

Sheet OpEx
A1: Operating Expenses — recurring overhead, founder draw & one-time setup
A2: Month | B2: 1 | C2: 2 | D2: 3 | E2: 4 | F2: 5 | G2: 6 | H2: 7 | I2: 8 | J2: 9 | K2: 10 | L2: 11 | M2: 12 | N2: 13 | O2: 14 | P2: 15 | Q2: 16 | R2: 17 | S2: 18
A3: Period | B3: Jul-26 | C3: Aug-26 | D3: Sep-26 | E3: Oct-26 | F3: Nov-26 | G3: Dec-26 | H3: Jan-27 | I3: Feb-27 | J3: Mar-27 | K3: Apr-27 | L3: May-27 | M3: Jun-27 | N3: Jul-27 | O3: Aug-27 | P3: Sep-27 | Q3: Oct-27 | R3: Nov-27 | S3: Dec-27
A5: OPERATING EXPENSES (standard categories)
A6: Founder living draw | B6: =Assumptions!$B$24 -> 6000 | C6: =Assumptions!$B$24 -> 6000 | D6: =Assumptions!$B$24 -> 6000 | E6: =Assumptions!$B$24 -> 6000 | F6: =Assumptions!$B$24 -> 6000 | G6: =Assumptions!$B$24 -> 6000 | H6: =Assumptions!$B$24 -> 6000 | I6: =Assumptions!$B$24 -> 6000 | ... S6: =Assumptions!$B$24 -> 6000
A7: Software & subscriptions | B7: =Assumptions!$B$25*(1+Assumptions!$B$26)^(B2-1) -> 350 | C7: =Assumptions!$B$25*(1+Assumptions!$B$26)^(C2-1) -> 360.5 | D7: =Assumptions!$B$25*(1+Assumptions!$B$26)^(D2-1) -> 371.315 | E7: =Assumptions!$B$25*(1+Assumptions!$B$26)^(E2-1) -> 382.45445 | F7: =Assumptions!$B$25*(1+Assumptions!$B$26)^(F2-1) -> 393.92808 | G7: =Assumptions!$B$25*(1+Assumptions!$B$26)^(G2-1) -> 405.74593 | H7: =Assumptions!$B$25*(1+Assumptions!$B$26)^(H2-1) -> 417.9183 | I7: =Assumptions!$B$25*(1+Assumptions!$B$26)^(I2-1) -> 430.45585 | ... S7: =Assumptions!$B$25*(1+Assumptions!$B$26)^(S2-1) -> 578.49667
A8: Sales & marketing | B8: =Assumptions!$B$27*(1+Assumptions!$B$28)^(B2-1) -> 300 | C8: =Assumptions!$B$27*(1+Assumptions!$B$28)^(C2-1) -> 315 | D8: =Assumptions!$B$27*(1+Assumptions!$B$28)^(D2-1) -> 330.75 | E8: =Assumptions!$B$27*(1+Assumptions!$B$28)^(E2-1) -> 347.2875 | F8: =Assumptions!$B$27*(1+Assumptions!$B$28)^(F2-1) -> 364.65188 | G8: =Assumptions!$B$27*(1+Assumptions!$B$28)^(G2-1) -> 382.88447 | H8: =Assumptions!$B$27*(1+Assumptions!$B$28)^(H2-1) -> 402.02869 | I8: =Assumptions!$B$27*(1+Assumptions!$B$28)^(I2-1) -> 422.13013 | ... S8: =Assumptions!$B$27*(1+Assumptions!$B$28)^(S2-1) -> 687.6055
A9: Accounting & bookkeeping | B9: =Assumptions!$B$29 -> 250 | C9: =Assumptions!$B$29 -> 250 | D9: =Assumptions!$B$29 -> 250 | E9: =Assumptions!$B$29 -> 250 | F9: =Assumptions!$B$29 -> 250 | G9: =Assumptions!$B$29 -> 250 | H9: =Assumptions!$B$29 -> 250 | I9: =Assumptions!$B$29 -> 250 | ... S9: =Assumptions!$B$29 -> 250
A10: Insurance (E&O / liability) | B10: =IF(B2>=Assumptions!$B$31,Assumptions!$B$30,0) -> 0 | C10: =IF(C2>=Assumptions!$B$31,Assumptions!$B$30,0) -> 0 | D10: =IF(D2>=Assumptions!$B$31,Assumptions!$B$30,0) -> 150 | E10: =IF(E2>=Assumptions!$B$31,Assumptions!$B$30,0) -> 150 | F10: =IF(F2>=Assumptions!$B$31,Assumptions!$B$30,0) -> 150 | G10: =IF(G2>=Assumptions!$B$31,Assumptions!$B$30,0) -> 150 | H10: =IF(H2>=Assumptions!$B$31,Assumptions!$B$30,0) -> 150 | I10: =IF(I2>=Assumptions!$B$31,Assumptions!$B$30,0) -> 150 | ... S10: =IF(S2>=Assumptions!$B$31,Assumptions!$B$30,0) -> 150
A11: Office / admin / misc | B11: =Assumptions!$B$32 -> 150 | C11: =Assumptions!$B$32 -> 150 | D11: =Assumptions!$B$32 -> 150 | E11: =Assumptions!$B$32 -> 150 | F11: =Assumptions!$B$32 -> 150 | G11: =Assumptions!$B$32 -> 150 | H11: =Assumptions!$B$32 -> 150 | I11: =Assumptions!$B$32 -> 150 | ... S11: =Assumptions!$B$32 -> 150
A12: Contract admin / VA | B12: =IF(B2>=Assumptions!$B$34,Assumptions!$B$33,0) -> 0 | C12: =IF(C2>=Assumptions!$B$34,Assumptions!$B$33,0) -> 0 | D12: =IF(D2>=Assumptions!$B$34,Assumptions!$B$33,0) -> 0 | E12: =IF(E2>=Assumptions!$B$34,Assumptions!$B$33,0) -> 0 | F12: =IF(F2>=Assumptions!$B$34,Assumptions!$B$33,0) -> 0 | G12: =IF(G2>=Assumptions!$B$34,Assumptions!$B$33,0) -> 0 | H12: =IF(H2>=Assumptions!$B$34,Assumptions!$B$33,0) -> 0 | I12: =IF(I2>=Assumptions!$B$34,Assumptions!$B$33,0) -> 0 | ... S12: =IF(S2>=Assumptions!$B$34,Assumptions!$B$33,0) -> 1200
A13: Founder Institute & business setup (one-time) | B13: =IF(B2=1,Assumptions!$B$37+Assumptions!$B$38+Assumptions!$B$39,0)+IF(B2=Assumptions!$B$41,Assumptions!$B$40,0) -> 1499 | C13: =IF(C2=1,Assumptions!$B$37+Assumptions!$B$38+Assumptions!$B$39,0)+IF(C2=Assumptions!$B$41,Assumptions!$B$40,0) -> 1500 | D13: =IF(D2=1,Assumptions!$B$37+Assumptions!$B$38+Assumptions!$B$39,0)+IF(D2=Assumptions!$B$41,Assumptions!$B$40,0) -> 0 | E13: =IF(E2=1,Assumptions!$B$37+Assumptions!$B$38+Assumptions!$B$39,0)+IF(E2=Assumptions!$B$41,Assumptions!$B$40,0) -> 0 | F13: =IF(F2=1,Assumptions!$B$37+Assumptions!$B$38+Assumptions!$B$39,0)+IF(F2=Assumptions!$B$41,Assumptions!$B$40,0) -> 0 | G13: =IF(G2=1,Assumptions!$B$37+Assumptions!$B$38+Assumptions!$B$39,0)+IF(G2=Assumptions!$B$41,Assumptions!$B$40,0) -> 0 | H13: =IF(H2=1,Assumptions!$B$37+Assumptions!$B$38+Assumptions!$B$39,0)+IF(H2=Assumptions!$B$41,Assumptions!$B$40,0) -> 0 | I13: =IF(I2=1,Assumptions!$B$37+Assumptions!$B$38+Assumptions!$B$39,0)+IF(I2=Assumptions!$B$41,Assumptions!$B$40,0) -> 0 | ... S13: =IF(S2=1,Assumptions!$B$37+Assumptions!$B$38+Assumptions!$B$39,0)+IF(S2=Assumptions!$B$41,Assumptions!$B$40,0) -> 0
A14: Total operating expenses | B14: =SUM(B6:B13) -> 8549 | C14: =SUM(C6:C13) -> 8575.5 | D14: =SUM(D6:D13) -> 7252.065 | E14: =SUM(E6:E13) -> 7279.742 | F14: =SUM(F6:F13) -> 7308.58 | G14: =SUM(G6:G13) -> 7338.6304 | H14: =SUM(H6:H13) -> 7369.947 | I14: =SUM(I6:I13) -> 7402.586 | ... S14: =SUM(S6:S13) -> 9016.1022

Sheet Cash Flow
A1: Cash Flow & Cash Needs — what the business burns and generates
A2: Month | B2: 1 | C2: 2 | D2: 3 | E2: 4 | F2: 5 | G2: 6 | H2: 7 | I2: 8 | J2: 9 | K2: 10 | L2: 11 | M2: 12 | N2: 13 | O2: 14 | P2: 15 | Q2: 16 | R2: 17 | S2: 18
A3: Period | B3: Jul-26 | C3: Aug-26 | D3: Sep-26 | E3: Oct-26 | F3: Nov-26 | G3: Dec-26 | H3: Jan-27 | I3: Feb-27 | J3: Mar-27 | K3: Apr-27 | L3: May-27 | M3: Jun-27 | N3: Jul-27 | O3: Aug-27 | P3: Sep-27 | Q3: Oct-27 | R3: Nov-27 | S3: Dec-27
A5: MONTHLY CASH FLOW
A6: Total revenue | B6: =Revenue!B26 -> 0 | C6: =Revenue!C26 -> 0 | D6: =Revenue!D26 -> 9800 | E6: =Revenue!E26 -> 10399 | F6: =Revenue!F26 -> 19886.02 | G6: =Revenue!G26 -> 21060.3 | H6: =Revenue!H26 -> 32011.094 | I6: =Revenue!I26 -> 61737.872 | ... S6: =Revenue!S26 -> 121786.18
A7: Less: cost of sales | B7: =-'Cost of Sales'!B10 -> 0 | C7: =-'Cost of Sales'!C10 -> 0 | D7: =-'Cost of Sales'!D10 -> -2935.1 | E7: =-'Cost of Sales'!E10 -> -2987.771 | F7: =-'Cost of Sales'!F10 -> -5873.0886 | G7: =-'Cost of Sales'!G10 -> -5976.3448 | H7: =-'Cost of Sales'!H10 -> -9012.6359 | I7: =-'Cost of Sales'!I10 -> -16976.474 | ... S7: =-'Cost of Sales'!S10 -> -29309.405
A8: Gross profit | B8: =B6+B7 -> 0 | C8: =C6+C7 -> 0 | D8: =D6+D7 -> 6864.9 | E8: =E6+E7 -> 7411.229 | F8: =F6+F7 -> 14012.931 | G8: =G6+G7 -> 15083.955 | H8: =H6+H7 -> 22998.458 | I8: =I6+I7 -> 44761.398 | ... S8: =S6+S7 -> 92476.771
A9: Less: operating expenses | B9: =-OpEx!B14 -> -8549 | C9: =-OpEx!C14 -> -8575.5 | D9: =-OpEx!D14 -> -7252.065 | E9: =-OpEx!E14 -> -7279.742 | F9: =-OpEx!F14 -> -7308.58 | G9: =-OpEx!G14 -> -7338.6304 | H9: =-OpEx!H14 -> -7369.947 | I9: =-OpEx!I14 -> -7402.586 | ... S9: =-OpEx!S14 -> -9016.1022
A10: Net cash flow | B10: =B8+B9 -> -8549 | C10: =C8+C9 -> -8575.5 | D10: =D8+D9 -> -387.165 | E10: =E8+E9 -> 131.48705 | F10: =F8+F9 -> 6704.3515 | G10: =G8+G9 -> 7745.3244 | H10: =H8+H9 -> 15628.511 | I10: =I8+I9 -> 37358.812 | ... S10: =S8+S9 -> 83460.669
A11: Cumulative cash position | B11: =B10 -> -8549 | C11: =B11+C10 -> -17124.5 | D11: =C11+D10 -> -17511.665 | E11: =D11+E10 -> -17380.178 | F11: =E11+F10 -> -10675.826 | G11: =F11+G10 -> -2930.5021 | H11: =G11+H10 -> 12698.009 | I11: =H11+I10 -> 50056.82 | J11: =I11+J10 -> 98207.453 | ... S11: =R11+S10 -> 687891.54
A17: SUMMARY — 18-MONTH CASH NEEDS
A18: Total revenue | B18: =SUM(B6:S6) -> 1125577.3
A19: Total cost of sales | B19: =SUM(B7:S7)*-1 -> 288452.03
A20: Total operating expenses | B20: =SUM(B9:S9)*-1 -> 149233.77
A21: Net cash generated (18 mo) | B21: =SUM(B10:S10) -> 687891.54
A22: Peak cumulative cash need (financing required) | B22: =-MIN(B11:S11) -> 17511.665
A23: Month of deepest cash position | B23: =MATCH(MIN(B11:S11),B11:S11,0) -> 3
A24: Cash-flow breakeven (first net-positive month) | B24: =MATCH(TRUE,INDEX(B10:S10>0,0),0) -> 4
A25: Ending cash position (Month 18) | B25: =S11 -> 687891.54
