Workbook

Sheet Instructions
B1: PhysicianLabs — Channel Test Tracker (2026-07)
B2: Test window: 2026-07-01 to 2026-07-21 · Channels: LinkedIn · Reddit/Communities · Cold Email
B4: How to use this workbook
B5: 1. Analytics (Plausible) and Netlify Forms capture TRAFFIC and SIGNUPS automatically once the page is live.
B6: 2. This tracker is where you log what those tools cannot see: your effort and your SPEND.
B7: 3. Channel Log tab — add one row per posting/sending run. Type into the shaded input columns only;
B8: CTR, cost-per-click, conversion rate, and cost-per-signup calculate themselves.
B9: 4. Weekly Rollup tab — updates automatically from Channel Log. This is your compare-the-channels view.
B10: 5. Expenses tab — log every tool subscription and any ad spend so the test has a true all-in cost.
B12: Where each number comes from
B13: Reach / Impressions → LinkedIn/Reddit/Facebook post analytics, or emails sent (Cold Email).
B14: Clicks → Plausible (segment by utm_source) or the platform link analytics.
... B22: Reminder: no PHI in any field. Follow each community’s promotion rules. CAN-SPAM on all cold email.

Sheet Channel Log
A1: Date | B1: Channel | C1: Content / Run | D1: Reach / Impressions | E1: Clicks | F1: Spend ($) | G1: Signups | H1: CTR | I1: Cost / Click | J1: Conv. Rate | K1: Cost / Signup | L1: Notes
H2: =IF(D2=0,"-",IF(D2="","",E2/D2)) | I2: =IF(E2=0,"-",F2/E2) | J2: =IF(E2=0,"-",G2/E2) | K2: =IF(G2=0,"-",F2/G2)
H3: =IF(D3=0,"-",IF(D3="","",E3/D3)) | I3: =IF(E3=0,"-",F3/E3) | J3: =IF(E3=0,"-",G3/E3) | K3: =IF(G3=0,"-",F3/G3)
H4: =IF(D4=0,"-",IF(D4="","",E4/D4)) | I4: =IF(E4=0,"-",F4/E4) | J4: =IF(E4=0,"-",G4/E4) | K4: =IF(G4=0,"-",F4/G4)
H5: =IF(D5=0,"-",IF(D5="","",E5/D5)) | I5: =IF(E5=0,"-",F5/E5) | J5: =IF(E5=0,"-",G5/E5) | K5: =IF(G5=0,"-",F5/G5)
H6: =IF(D6=0,"-",IF(D6="","",E6/D6)) | I6: =IF(E6=0,"-",F6/E6) | J6: =IF(E6=0,"-",G6/E6) | K6: =IF(G6=0,"-",F6/G6)
H7: =IF(D7=0,"-",IF(D7="","",E7/D7)) | I7: =IF(E7=0,"-",F7/E7) | J7: =IF(E7=0,"-",G7/E7) | K7: =IF(G7=0,"-",F7/G7)
H8: =IF(D8=0,"-",IF(D8="","",E8/D8)) | I8: =IF(E8=0,"-",F8/E8) | J8: =IF(E8=0,"-",G8/E8) | K8: =IF(G8=0,"-",F8/G8)
H9: =IF(D9=0,"-",IF(D9="","",E9/D9)) | I9: =IF(E9=0,"-",F9/E9) | J9: =IF(E9=0,"-",G9/E9) | K9: =IF(G9=0,"-",F9/G9)
H10: =IF(D10=0,"-",IF(D10="","",E10/D10)) | I10: =IF(E10=0,"-",F10/E10) | J10: =IF(E10=0,"-",G10/E10) | K10: =IF(G10=0,"-",F10/G10)
H11: =IF(D11=0,"-",IF(D11="","",E11/D11)) | I11: =IF(E11=0,"-",F11/E11) | J11: =IF(E11=0,"-",G11/E11) | K11: =IF(G11=0,"-",F11/G11)
H12: =IF(D12=0,"-",IF(D12="","",E12/D12)) | I12: =IF(E12=0,"-",F12/E12) | J12: =IF(E12=0,"-",G12/E12) | K12: =IF(G12=0,"-",F12/G12)
H13: =IF(D13=0,"-",IF(D13="","",E13/D13)) | I13: =IF(E13=0,"-",F13/E13) | J13: =IF(E13=0,"-",G13/E13) | K13: =IF(G13=0,"-",F13/G13)
... H201: =IF(D201=0,"-",IF(D201="","",E201/D201)) | I201: =IF(E201=0,"-",F201/E201) | J201: =IF(E201=0,"-",G201/E201) | K201: =IF(G201=0,"-",F201/G201)

Sheet Weekly Rollup
A1: Channel | B1: Reach / Impr. | C1: Clicks | D1: Spend ($) | E1: Signups | F1: CTR | G1: Cost / Click | H1: Conv. Rate | I1: Cost / Signup
A2: LinkedIn | B2: =SUMIF('Channel Log'!$B$2:$B$201,$A2,'Channel Log'!$D$2:$D$201) | C2: =SUMIF('Channel Log'!$B$2:$B$201,$A2,'Channel Log'!$E$2:$E$201) | D2: =SUMIF('Channel Log'!$B$2:$B$201,$A2,'Channel Log'!$F$2:$F$201) | E2: =SUMIF('Channel Log'!$B$2:$B$201,$A2,'Channel Log'!$G$2:$G$201) | F2: =IF(B2=0,"-",C2/B2) | G2: =IF(C2=0,"-",D2/C2) | H2: =IF(C2=0,"-",E2/C2) | I2: =IF(E2=0,"-",D2/E2)
A3: Reddit | B3: =SUMIF('Channel Log'!$B$2:$B$201,$A3,'Channel Log'!$D$2:$D$201) | C3: =SUMIF('Channel Log'!$B$2:$B$201,$A3,'Channel Log'!$E$2:$E$201) | D3: =SUMIF('Channel Log'!$B$2:$B$201,$A3,'Channel Log'!$F$2:$F$201) | E3: =SUMIF('Channel Log'!$B$2:$B$201,$A3,'Channel Log'!$G$2:$G$201) | F3: =IF(B3=0,"-",C3/B3) | G3: =IF(C3=0,"-",D3/C3) | H3: =IF(C3=0,"-",E3/C3) | I3: =IF(E3=0,"-",D3/E3)
A4: Facebook | B4: =SUMIF('Channel Log'!$B$2:$B$201,$A4,'Channel Log'!$D$2:$D$201) | C4: =SUMIF('Channel Log'!$B$2:$B$201,$A4,'Channel Log'!$E$2:$E$201) | D4: =SUMIF('Channel Log'!$B$2:$B$201,$A4,'Channel Log'!$F$2:$F$201) | E4: =SUMIF('Channel Log'!$B$2:$B$201,$A4,'Channel Log'!$G$2:$G$201) | F4: =IF(B4=0,"-",C4/B4) | G4: =IF(C4=0,"-",D4/C4) | H4: =IF(C4=0,"-",E4/C4) | I4: =IF(E4=0,"-",D4/E4)
A5: Cold Email | B5: =SUMIF('Channel Log'!$B$2:$B$201,$A5,'Channel Log'!$D$2:$D$201) | C5: =SUMIF('Channel Log'!$B$2:$B$201,$A5,'Channel Log'!$E$2:$E$201) | D5: =SUMIF('Channel Log'!$B$2:$B$201,$A5,'Channel Log'!$F$2:$F$201) | E5: =SUMIF('Channel Log'!$B$2:$B$201,$A5,'Channel Log'!$G$2:$G$201) | F5: =IF(B5=0,"-",C5/B5) | G5: =IF(C5=0,"-",D5/C5) | H5: =IF(C5=0,"-",E5/C5) | I5: =IF(E5=0,"-",D5/E5)
A6: Paid Boost | B6: =SUMIF('Channel Log'!$B$2:$B$201,$A6,'Channel Log'!$D$2:$D$201) | C6: =SUMIF('Channel Log'!$B$2:$B$201,$A6,'Channel Log'!$E$2:$E$201) | D6: =SUMIF('Channel Log'!$B$2:$B$201,$A6,'Channel Log'!$F$2:$F$201) | E6: =SUMIF('Channel Log'!$B$2:$B$201,$A6,'Channel Log'!$G$2:$G$201) | F6: =IF(B6=0,"-",C6/B6) | G6: =IF(C6=0,"-",D6/C6) | H6: =IF(C6=0,"-",E6/C6) | I6: =IF(E6=0,"-",D6/E6)
A7: Other | B7: =SUMIF('Channel Log'!$B$2:$B$201,$A7,'Channel Log'!$D$2:$D$201) | C7: =SUMIF('Channel Log'!$B$2:$B$201,$A7,'Channel Log'!$E$2:$E$201) | D7: =SUMIF('Channel Log'!$B$2:$B$201,$A7,'Channel Log'!$F$2:$F$201) | E7: =SUMIF('Channel Log'!$B$2:$B$201,$A7,'Channel Log'!$G$2:$G$201) | F7: =IF(B7=0,"-",C7/B7) | G7: =IF(C7=0,"-",D7/C7) | H7: =IF(C7=0,"-",E7/C7) | I7: =IF(E7=0,"-",D7/E7)
A8: TOTAL | B8: =SUM(B2:B7) | C8: =SUM(C2:C7) | D8: =SUM(D2:D7) | E8: =SUM(E2:E7) | F8: =IF(B8=0,"-",C8/B8) | G8: =IF(C8=0,"-",D8/C8) | H8: =IF(C8=0,"-",E8/C8) | I8: =IF(E8=0,"-",D8/E8)

Sheet Expenses
A1: Date | B1: Item | C1: Category | D1: Channel | E1: Amount ($) | F1: Notes
A2: 2026-07-01 | B2: LinkedIn Sales Navigator | C2: Tooling | D2: LinkedIn | E2: 99 | F2: Monthly — ICP search + InMail
A3: 2026-07-01 | B3: Cold email sequencer (Instantly/Smartlead) | C3: Tooling | D3: Cold Email | E3: 60 | F3: Monthly — warmup + sending
A4: 2026-07-01 | B4: Email list verification | C4: Tooling | D4: Cold Email | E4: 30 | F4: One-time — clean the prospect CSV
A5: 2026-07-01 | B5: Plausible Analytics | C5: Tooling | D5: Other | E5: 9 | F5: Monthly — traffic measurement
D61: TOTAL | E61: =SUM(E2:E60)
